ament_cmake_include_directories/_dummy.cpython-310-x86_64-linux-gnu.so
ros_ament_cmake_include_directories-2.7.3.data/data/share/ament_cmake_include_directories/local_setup.bash
ros_ament_cmake_include_directories-2.7.3.data/data/share/ament_cmake_include_directories/local_setup.dsv
ros_ament_cmake_include_directories-2.7.3.data/data/share/ament_cmake_include_directories/local_setup.sh
ros_ament_cmake_include_directories-2.7.3.data/data/share/ament_cmake_include_directories/local_setup.zsh
ros_ament_cmake_include_directories-2.7.3.data/data/share/ament_cmake_include_directories/package.dsv
ros_ament_cmake_include_directories-2.7.3.data/data/share/ament_cmake_include_directories/package.xml
ros_ament_cmake_include_directories-2.7.3.data/data/share/ament_cmake_include_directories/cmake/ament_cmake_include_directories-extras.cmake
ros_ament_cmake_include_directories-2.7.3.data/data/share/ament_cmake_include_directories/cmake/ament_cmake_include_directoriesConfig-version.cmake
ros_ament_cmake_include_directories-2.7.3.data/data/share/ament_cmake_include_directories/cmake/ament_cmake_include_directoriesConfig.cmake
ros_ament_cmake_include_directories-2.7.3.data/data/share/ament_cmake_include_directories/cmake/ament_include_directories_order.cmake
ros_ament_cmake_include_directories-2.7.3.data/data/share/ament_cmake_include_directories/environment/ament_prefix_path.dsv
ros_ament_cmake_include_directories-2.7.3.data/data/share/ament_cmake_include_directories/environment/ament_prefix_path.sh
ros_ament_cmake_include_directories-2.7.3.data/data/share/ament_cmake_include_directories/environment/path.dsv
ros_ament_cmake_include_directories-2.7.3.data/data/share/ament_cmake_include_directories/environment/path.sh
ros_ament_cmake_include_directories-2.7.3.data/data/share/ament_index/resource_index/package_run_dependencies/ament_cmake_include_directories
ros_ament_cmake_include_directories-2.7.3.dist-info/METADATA
ros_ament_cmake_include_directories-2.7.3.dist-info/WHEEL
ros_ament_cmake_include_directories-2.7.3.dist-info/top_level.txt
ros_ament_cmake_include_directories-2.7.3.dist-info/RECORD
