Metadata-Version: 2.4
Name: ros-ament-cmake-include-directories
Version: 2.7.3
Summary: Wheel for the ament_cmake_include_directories (ros-ament-cmake-include-directories) ROS 2 package.
Dynamic: description
Dynamic: description-content-type
Dynamic: summary
